cartesio/__init__.py
cartesio/callback.py
cartesio/dataset.py
cartesio/easy.py
cartesio/endpoint.py
cartesio/enums.py
cartesio/export.py
cartesio/fitness.py
cartesio/inference.py
cartesio/metric.py
cartesio/mutation.py
cartesio/plot.py
cartesio/population.py
cartesio/strategy.py
cartesio/training.py
cartesio/applications/CGPC.py
cartesio/applications/CGPClass.py
cartesio/applications/CGPIP.py
cartesio/applications/CGPW.py
cartesio/applications/__init__.py
cartesio/cli/__init__.py
cartesio/cli/init_dataset.py
cartesio/core/__init__.py
cartesio/core/bundle.py
cartesio/core/callback.py
cartesio/core/decoder.py
cartesio/core/endpoint.py
cartesio/core/evolution.py
cartesio/core/genome.py
cartesio/core/helper.py
cartesio/core/model.py
cartesio/core/mutation.py
cartesio/core/node.py
cartesio/core/population.py
cartesio/image/__init__.py
cartesio/image/bundle.py
cartesio/image/catalog.py
cartesio/image/kernel.py
cartesio/image/nodes.py
cartesio/utils/__init__.py
cartesio/utils/json_utils.py
cartesio/utils/saving.py
cartesio/utils/stacking.py
cartesio/utils/viewer.py
cartesio_python-0.9.6.1.dist-info/LICENSE
cartesio_python-0.9.6.1.dist-info/METADATA
cartesio_python-0.9.6.1.dist-info/WHEEL
cartesio_python-0.9.6.1.dist-info/entry_points.txt
cartesio_python-0.9.6.1.dist-info/top_level.txt
cartesio_python-0.9.6.1.dist-info/RECORD
