Metadata-Version: 2.1
Name: cartesio-python
Version: 0.9.6.1
Summary: Cartesio is a simple Cartesian Genetic Programming python package to solve Image Segmentation problems.
Home-page: UNKNOWN
Author: Kevin Cortacero
Author-email: kevin.cortacero@inserm.fr
Maintainer: Kevin Cortacero
Maintainer-email: kevin.cortacero@inserm.fr
License: MIT
Project-URL: Source, https://github.com/MicroMedIAn/cartesio
Project-URL: Tracker, https://github.com/MicroMedIAn/cartesio/issues
Keywords: genetic algorithm,machine learning,segmentation,computer vision
Platform: any
Classifier: Programming Language :: Python :: 3.7
License-File: LICENSE
Requires-Dist: numpy
Requires-Dist: opencv-python
Requires-Dist: scikit-image
Requires-Dist: matplotlib
Requires-Dist: numba
Requires-Dist: simplejson
Requires-Dist: micromind
Requires-Dist: tifffile
Requires-Dist: roifile
